tchoice/__init__.py
tchoice-0.0.1.dist-info/LICENSE
tchoice-0.0.1.dist-info/METADATA
tchoice-0.0.1.dist-info/WHEEL
tchoice-0.0.1.dist-info/top_level.txt
tchoice-0.0.1.dist-info/RECORD
