Metadata-Version: 2.2
Name: tchoice
Version: 0.0.1
Summary: TChoice - Lightweight implementation of Django-like `TextChoices` and `IntegerChoices`.
Home-page: https://github.com/ispaneli/tchoice
Author: Ilya Antonov
Author-email: ispanelki@gmail.com
Project-URL: Issue Tracker, https://github.com/ispaneli/tchoice/issues
Project-URL: Source, https://github.com/ispaneli/tchoice/tree/master/src/tchoice
Project-URL: Say Thanks!, http://saythanks.io/to/ispanelki
Project-URL: Documentation, https://github.com/ispaneli/tchoice
Keywords: django,textchoices,intchoices,backend,fastapi,microservice,typing,enum,dataclass,dataclasses,pydantic
Classifier: Development Status :: 4 - Beta
Classifier: Environment :: Other Environment
Classifier: License :: OSI Approved :: MIT License
Classifier: Operating System :: OS Independent
Classifier: Programming Language :: Python
Classifier: Programming Language :: Python :: 3
Classifier: Programming Language :: Python :: 3 :: Only
Classifier: Programming Language :: Python :: 3.11
Classifier: Programming Language :: Python :: 3.12
Classifier: Programming Language :: Python :: 3.13
Classifier: Topic :: Software Development
Classifier: Topic :: Software Development :: Libraries
Classifier: Topic :: Software Development :: Libraries :: Python Modules
Classifier: Typing :: Typed
Requires-Python: <4,>=3.11
License-File: LICENSE
